docs/Makefile
docs/make.bat
docs/build/doctrees/change_log.doctree
docs/build/doctrees/changes.doctree
docs/build/doctrees/environment.pickle
docs/build/doctrees/index.doctree
docs/build/doctrees/modules.doctree
docs/build/doctrees/overview.doctree
docs/build/doctrees/quanfima.doctree
docs/build/doctrees/quickstart.doctree
docs/build/doctrees/setup.doctree
docs/build/html/.buildinfo
docs/build/html/.nojekyll
docs/build/html/change_log.html
docs/build/html/changes.html
docs/build/html/genindex.html
docs/build/html/index.html
docs/build/html/modules.html
docs/build/html/objects.inv
docs/build/html/overview.html
docs/build/html/py-modindex.html
docs/build/html/quanfima.html
docs/build/html/quickstart.html
docs/build/html/search.html
docs/build/html/searchindex.js
docs/build/html/setup.html
docs/build/html/_images/2d_polymer_data.png
docs/build/html/_images/2d_polymer_diameter_map.png
docs/build/html/_images/2d_polymer_orientation_map.png
docs/build/html/_images/dataset_w36_3d_diameter.png
docs/build/html/_images/dataset_w36_3d_orientation.png
docs/build/html/_images/polymer_w32_3d_diameter.png
docs/build/html/_images/polymer_w32_3d_orientation.png
docs/build/html/_modules/index.html
docs/build/html/_modules/quanfima/morphology.html
docs/build/html/_modules/quanfima/simulation.html
docs/build/html/_modules/quanfima/utils.html
docs/build/html/_modules/quanfima/visualization.html
docs/build/html/_sources/change_log.rst.txt
docs/build/html/_sources/changes.rst.txt
docs/build/html/_sources/index.rst.txt
docs/build/html/_sources/modules.rst.txt
docs/build/html/_sources/overview.rst.txt
docs/build/html/_sources/quanfima.rst.txt
docs/build/html/_sources/quickstart.rst.txt
docs/build/html/_sources/setup.rst.txt
docs/build/html/_static/2d_polymer_data.png
docs/build/html/_static/2d_polymer_diameter_map.png
docs/build/html/_static/2d_polymer_diameter_map_600px.png
docs/build/html/_static/2d_polymer_orientation_map.png
quanfima-0.1a3.dist-info/DESCRIPTION.rst
quanfima-0.1a3.dist-info/METADATA
quanfima-0.1a3.dist-info/RECORD
quanfima-0.1a3.dist-info/WHEEL
quanfima-0.1a3.dist-info/metadata.json
quanfima-0.1a3.dist-info/top_level.txt
