Metadata-Version: 2.0
Name: quanfima
Version: 0.1a3
Summary: The package for morphological analysis and visualization of fibrous materials.
Home-page: http://github.com/rshkarin/quanfima
Author: Roman Shkarin, Andrei Shkarin
Author-email: roman.v.shkarin@gmail.com, andrei.shkarin@gmail.com
License: MIT
Keywords: biomaterials fiber analysis material science visualization
Platform: UNKNOWN
Classifier: Development Status :: 3 - Alpha
Classifier: License :: OSI Approved :: MIT License
Classifier: Programming Language :: Python :: 2.7
Classifier: Topic :: Scientific/Engineering :: Information Analysis
Requires-Python: >=2.6,<3
Requires-Dist: matplotlib (==2.0.2)
Requires-Dist: numpy (>=1.13.3)
Requires-Dist: pandas (>=0.19.2)
Requires-Dist: scikit-image (>=0.12.3)
Requires-Dist: scikit-learn (>=0.18.1)
Requires-Dist: scipy (>=0.19.0)
Requires-Dist: imageio (>=2.3.0)
